yschema/__init__.py
yschema/__main__.py
yschema/exceptions.py
yschema/schema.py
yschema/types.py
yschema-1.0.2.dist-info/METADATA
yschema-1.0.2.dist-info/RECORD
yschema-1.0.2.dist-info/WHEEL
yschema-1.0.2.dist-info/entry_points.txt
yschema-1.0.2.dist-info/top_level.txt
yschema-1.0.2.dist-info/zip-safe
