Metadata-Version: 2.1
Name: yschema
Version: 1.0.2
Summary: A YAML/JSON/dictionary schema validator with terse schema definitions
Home-page: https://bitbucket.org/trlandet/yschema
Author: Tormod Landet
Author-email: tormod@landet.net
License: Apache 2.0
Keywords: yaml json schema validation
Platform: UNKNOWN
Classifier: Development Status :: 5 - Production/Stable
Classifier: Intended Audience :: Developers
Classifier: Topic :: Software Development :: Libraries
Classifier: Topic :: Software Development :: Pre-processors
Classifier: Topic :: Software Development :: Quality Assurance
Classifier: License :: OSI Approved :: Apache Software License
Classifier: Programming Language :: Python :: 3
Requires-Dist: PyYAML
